Metadata-Version: 2.1
Name: torchplot
Version: 0.1.7
Summary: Plotting pytorch tensors made easy
Home-page: UNKNOWN
Author: Nicki Skafte Detlefsen et al.
Author-email: nsde@dtu.dk
License: Apache-2.0
Download-URL: https://github.com/CenterBioML/torchplot/archive/0.1.7.zip
Platform: UNKNOWN
Classifier: Environment :: Console
Classifier: Natural Language :: English
Classifier: Development Status :: 3 - Alpha
Classifier: Intended Audience :: Developers
Classifier: Topic :: Scientific/Engineering :: Artificial Intelligence
Classifier: License :: OSI Approved :: Apache Software License
Classifier: Operating System :: OS Independent
Classifier: Programming Language :: Python :: 3
Requires-Python: >=3
